{"id":"428835640537739_572765659478069","type":"video","created_time":"2013-11-13T16:21:29+0000","message":"\u099c\u09be\u09ae\u09be\u09df\u09be\u09a4\u09c7\u09b0 \u0986\u09ae\u09c0\u09b0 \u09ae\u09a4\u09bf\u0989\u09b0 \u09b0\u09b9\u09ae\u09be\u09a8 \u09a8\u09bf\u099c\u09be\u09ae\u09c0\u09b0 \u09b8\u09c1\u09af\u09cb\u0997\u09cd\u09af \u09b8\u09a8\u09cd\u09a4\u09be\u09a8 \u09ac\u09bf\u09b6\u09cd\u09ac \u09ae\u09bf\u09a1\u09bf\u09df\u09be\u09b0 \u09b8\u09be\u09ae\u09a8\u09c7 \u098f\u0995 \u09aa\u09cd\u09b0\u09c7\u09b8 \u0995\u09a8\u09ab\u09be\u09b0\u09c7\u09a8\u09cd\u09b8\u09c7 \u09a4\u09be\u09b0 \u09ac\u09be\u09ac\u09be \u09b8\u09ae\u09cd\u09aa\u09b0\u09cd\u0995\u09c7 \u09ac\u0995\u09cd\u09a4\u09ac\u09cd\u09af \u09a6\u09bf\u099a\u09cd\u099b\u09c7\u09a8.......","picture":"http:\/\/external.ak.fbcdn.net\/safe_image.php?d=AQCQzl3ydaW19Pj-&w=130&h=130&url=http%3A%2F%2Fi1.ytimg.com%2Fvi%2FsTEQK6uMT24%2Fhqdefault.jpg%3Ffeature%3Dog","source":"http:\/\/www.youtube.com\/v\/sTEQK6uMT24?autohide=1&version=3&autoplay=1","name":"Son Of Motiur Rahman Nizami in a Press Conference"}